odoo/addons/sale_commission/README.rst
odoo/addons/sale_commission/__init__.py
odoo/addons/sale_commission/__manifest__.py
odoo/addons/sale_commission/demo/sale_agent_demo.xml
odoo/addons/sale_commission/i18n/ca.po
odoo/addons/sale_commission/i18n/de.po
odoo/addons/sale_commission/i18n/es.po
odoo/addons/sale_commission/i18n/es_AR.po
odoo/addons/sale_commission/i18n/fi.po
odoo/addons/sale_commission/i18n/it.po
odoo/addons/sale_commission/i18n/nl_NL.po
odoo/addons/sale_commission/i18n/pt.po
odoo/addons/sale_commission/i18n/pt_BR.po
odoo/addons/sale_commission/i18n/pt_PT.po
odoo/addons/sale_commission/i18n/sale_commission.pot
odoo/addons/sale_commission/i18n/sl.po
odoo/addons/sale_commission/i18n/zh_CN.po
odoo/addons/sale_commission/migrations/13.0.1.0.0/noupdate_changes.xml
odoo/addons/sale_commission/migrations/13.0.1.0.0/post-migration.py
odoo/addons/sale_commission/migrations/13.0.1.0.0/pre-migration.py
odoo/addons/sale_commission/migrations/13.0.1.2.0/pre-migration.py
odoo/addons/sale_commission/migrations/13.0.1.6.0/pre-migration.py
odoo/addons/sale_commission/models/__init__.py
odoo/addons/sale_commission/models/account_move.py
odoo/addons/sale_commission/models/product_template.py
odoo/addons/sale_commission/models/res_partner.py
odoo/addons/sale_commission/models/sale_commission.py
odoo/addons/sale_commission/models/sale_commission_mixin.py
odoo/addons/sale_commission/models/sale_order.py
odoo/addons/sale_commission/models/settlement.py
odoo/addons/sale_commission/readme/CONFIGURE.rst
odoo/addons/sale_commission/readme/CONTRIBUTORS.rst
odoo/addons/sale_commission/readme/DESCRIPTION.rst
odoo/addons/sale_commission/readme/ROADMAP.rst
odoo/addons/sale_commission/readme/USAGE.rst
odoo/addons/sale_commission/report/__init__.py
odoo/addons/sale_commission/report/sale_commission_analysis_report.py
odoo/addons/sale_commission/report/sale_commission_analysis_report_view.xml
odoo/addons/sale_commission/security/ir.model.access.csv
odoo13_addon_sale_commission-13.0.1.8.0.dist-info/METADATA
odoo13_addon_sale_commission-13.0.1.8.0.dist-info/WHEEL
odoo13_addon_sale_commission-13.0.1.8.0.dist-info/top_level.txt
odoo13_addon_sale_commission-13.0.1.8.0.dist-info/RECORD
